{
  "success": true,
  "error": null,
  "results": {
    "keys": [ "FIPSCode", "Average TAT-RequestLevel(Days)", "County", "State" ],
    "data": [
      [ "06071", 15690, "San Bernardino", "CA" ],
      [ "17093", 623, "Kendall", "IL" ],
      [ "06037", 50964 ],
      [ "32007", 191 ],
      [ "06111", 3806 ],
      [ "17031", 45828 ],
      [ "06095", 3100 ],
      [ "06059", 23225 ],
      [ "31055", 2273 ],
      [ "06113", 1520 ],
      [ "06007", 1222 ],
      [ "04013", 20525 ],
      [ "48113", 13804 ],
      [ "48037", 333 ],
      [ "20037", 119 ],
      [ "21111", 2629 ],
      [ "11001", 4140 ],
      [ "22105", 222 ],
      [ "22109", 401 ],
      [ "22115", 383 ],
      [ "35013", 804 ],
      [ "26049", 1213 ],
      [ "48439", 15026 ],
      [ "27123", 2687 ],
      [ "17197", 3964 ],
      [ "09003", 321 ],
      [ "06085", 11881 ],
      [ "06013", 8068 ],
      [ "06083", 1993 ],
      [ "06081", 5430 ],
      [ "06055", 755 ],
      [ "06087", 1402 ],
      [ "06075", 7178 ],
      [ "48183", 594 ],
      [ "25025", 5087 ],
      [ "22045", 180 ],
      [ "34013", 268 ],
      [ "04015", 824 ],
      [ "48453", 7385 ],
      [ "17201", 935 ],
      [ "48099", 618 ],
      [ "18089", 3340 ],
      [ "51750", 82 ],
      [ "54005", 144 ],
      [ "54101", 90 ],
      [ "54019", 416 ],
      [ "28049", 1203 ],
      [ "18039", 633 ],
      [ "30049", 273 ],
      [ "35001", 15901 ],
      [ "47157", 5724 ],
      [ "06061", 1998 ],
      [ "12073", 618 ],
      [ "42101", 4823 ],
      [ "30063", 734 ],
      [ "30061", 8 ],
      [ "19033", 101 ],
      [ "45003", 442 ],
      [ "17127", 38 ],
      [ "22033", 4578 ],
      [ "02020", 2187 ],
      [ "42133", 1372 ],
      [ "55097", 2003 ],
      [ "51810", 3129 ],
      [ "48423", 1011 ],
      [ "40109", 2395 ],
      [ "48073", 163 ],
      [ "18127", 1134 ],
      [ "33017", 412 ],
      [ "23031", 404 ],
      [ "06053", 1636 ],
      [ "17141", 152 ],
      [ "44005", 2131 ],
      [ "47037", 3568 ],
      [ "21085", 23 ],
      [ "26061", 110 ],
      [ "12005", 216 ],
      [ "47119", 407 ],
      [ "39045", 841 ],
      [ "20167", 79 ],
      [ "39129", 233 ],
      [ "47057", 36 ],
      [ "47147", 215 ],
      [ "04027", 631 ],
      [ "47065", 1379 ],
      [ "47011", 298 ],
      [ "42089", 546 ],
      [ "54067", 287 ],
      [ "55079", 4861 ],
      [ "06009", 207 ],
      [ "48157", 2593 ],
      [ "45091", 883 ],
      [ "16011", 207 ],
      [ "39093", 613 ],
      [ "53033", 27132 ],
      [ "18065", 202 ],
      [ "21067", 1569 ],
      [ "51165", 113 ],
      [ "42015", 56 ],
      [ "48135", 544 ],
      [ "23019", 212 ],
      [ "51650", 1168 ],
      [ "06097", 2276 ],
      [ "26165", 83 ],
      [ "26087", 269 ],
      [ "16083", 838 ],
      [ "16053", 240 ],
      [ "45025", 58 ],
      [ "48367", 852 ],
      [ "22077", 31 ],
      [ "21161", 25 ],
      [ "02090", 625 ],
      [ "48409", 273 ],
      [ "10005", 809 ],
      [ "45013", 900 ],
      [ "55087", 2041 ],
      [ "39035", 3257 ],
      [ "17119", 1551 ],
      [ "17113", 1372 ],
      [ "48013", 169 ],
      [ "39113", 2262 ],
      [ "51550", 1633 ],
      [ "16001", 3069 ],
      [ "54039", 2038 ],
      [ "42075", 229 ],
      [ "51013", 1457 ],
      [ "32031", 6497 ],
      [ "42021", 229 ],
      [ "54011", 487 ],
      [ "55131", 297 ],
      [ "06017", 993 ],
      [ "51800", 464 ],
      [ "30031", 967 ],
      [ "51153", 11263 ],
      [ "49005", 666 ],
      [ "45007", 345 ],
      [ "51600", 63 ],
      [ "21035", 77 ],
      [ "06099", 1932 ],
      [ "42033", 92 ],
      [ "39165", 718 ],
      [ "47149", 1040 ],
      [ "49045", 349 ],
      [ "27067", 442 ],
      [ "47165", 647 ],
      [ "32510", 236 ],
      [ "17091", 573 ],
      [ "06019", 3363 ],
      [ "26017", 186 ],
      [ "48187", 512 ],
      [ "48463", 347 ],
      [ "35005", 201 ],
      [ "02100", 4 ],
      [ "51117", 119 ],
      [ "22001", 132 ],
      [ "51540", 267 ],
      [ "51127", 88 ],
      [ "42097", 133 ],
      [ "48339", 1674 ],
      [ "49011", 1622 ],
      [ "48465", 126 ],
      [ "51021", 21 ],
      [ "35043", 621 ],
      [ "17157", 84 ],
      [ "21167", 171 ],
      [ "21047", 599 ],
      [ "45019", 2133 ],
      [ "06045", 253 ],
      [ "51770", 299 ],
      [ "25013", 1372 ],
      [ "22097", 239 ],
      [ "17167", 545 ],
      [ "26143", 73 ],
      [ "51107", 1318 ],
      [ "36055", 247 ],
      [ "10003", 13308 ],
      [ "26147", 547 ],
      [ "51155", 50 ],
      [ "48251", 1250 ],
      [ "48245", 776 ],
      [ "30013", 529 ],
      [ "16027", 1315 ],
      [ "20169", 371 ],
      [ "31111", 136 ],
      [ "47093", 1338 ],
      [ "17147", 38 ],
      [ "17115", 613 ],
      [ "48491", 2948 ],
      [ "18035", 511 ],
      [ "18079", 64 ],
      [ "42103", 192 ],
      [ "33013", 337 ],
      [ "26139", 905 ],
      [ "55017", 389 ],
      [ "48139", 664 ],
      [ "47047", 135 ],
      [ "54061", 308 ],
      [ "42107", 208 ],
      [ "27025", 176 ],
      [ "39017", 1316 ],
      [ "42087", 62 ],
      [ "04021", 1882 ],
      [ "45079", 1552 ],
      [ "08013", 113 ],
      [ "24015", 15 ],
      [ "21177", 90 ],
      [ "55105", 334 ],
      [ "22057", 332 ],
      [ "47179", 334 ],
      [ "16019", 467 ],
      [ "32005", 189 ],
      [ "45059", 284 ],
      [ "17019", 1383 ],
      [ "19045", 116 ],
      [ "26051", 51 ],
      [ "55035", 515 ],
      [ "19121", 34 ],
      [ "35047", 97 ],
      [ "45021", 88 ],
      [ "27057", 14 ],
      [ "28059", 402 ],
      [ "31109", 864 ],
      [ "30043", 38 ],
      [ "32019", 203 ],
      [ "13021", 55 ],
      [ "48209", 1297 ],
      [ "51069", 223 ],
      [ "56033", 67 ],
      [ "18131", 34 ],
      [ "21059", 852 ],
      [ "40079", 105 ],
      [ "56001", 781 ],
      [ "48231", 376 ],
      [ "50001", 88 ],
      [ "21093", 618 ],
      [ "48449", 65 ],
      [ "28035", 278 ],
      [ "51095", 336 ],
      [ "17049", 107 ],
      [ "51161", 234 ],
      [ "27105", 53 ],
      [ "51115", 21 ],
      [ "40147", 151 ],
      [ "18151", 88 ],
      [ "44003", 541 ],
      [ "23011", 179 ],
      [ "48217", 196 ],
      [ "18053", 236 ],
      [ "21227", 995 ],
      [ "40115", 83 ],
      [ "39125", 33 ],
      [ "27171", 380 ],
      [ "45067", 76 ],
      [ "28033", 701 ],
      [ "50011", 71 ],
      [ "19113", 1068 ],
      [ "20151", 21 ],
      [ "48397", 439 ],
      [ "04007", 237 ],
      [ "08001", 92 ],
      [ "08035", 81 ],
      [ "08031", 314 ],
      [ "08117", 21 ],
      [ "08019", 12 ],
      [ "08123", 29 ],
      [ "08087", 13 ],
      [ "08017", 8 ],
      [ "08061", 8 ],
      [ "08089", 8 ],
      [ "08011", 8 ],
      [ "08099", 13 ],
      [ "08067", 19 ],
      [ "08109", 9 ],
      [ "08051", 13 ],
      [ "08113", 10 ],
      [ "08103", 13 ],
      [ "26023", 114 ],
      [ "55139", 2222 ],
      [ "48375", 1098 ],
      [ "27129", 63 ],
      [ "39055", 159 ],
      [ "51171", 93 ],
      [ "48303", 1502 ],
      [ "19103", 2745 ],
      [ "41051", 3177 ],
      [ "39025", 928 ],
      [ "17133", 159 ],
      [ "12115", 313 ],
      [ "20173", 4093 ],
      [ "48057", 37 ],
      [ "47189", 414 ],
      [ "39081", 192 ],
      [ "17159", 30 ],
      [ "31019", 168 ],
      [ "16061", 45 ],
      [ "18057", 1463 ],
      [ "49053", 748 ],
      [ "21087", 14 ],
      [ "18181", 90 ],
      [ "28047", 776 ],
      [ "12055", 91 ],
      [ "45009", 50 ],
      [ "28027", 140 ],
      [ "19117", 17 ],
      [ "51730", 261 ],
      [ "23013", 66 ],
      [ "02180", 56 ],
      [ "06023", 508 ],
      [ "17199", 266 ],
      [ "21151", 357 ],
      [ "17073", 141 ],
      [ "55109", 250 ],
      [ "45037", 74 ],
      [ "48069", 27 ],
      [ "48117", 167 ],
      [ "48315", 34 ],
      [ "47021", 152 ],
      [ "47005", 23 ],
      [ "28075", 217 ],
      [ "16017", 263 ],
      [ "18095", 418 ],
      [ "18135", 44 ],
      [ "17143", 1045 ],
      [ "19187", 104 ],
      [ "42045", 1609 ],
      [ "45077", 295 ],
      [ "18027", 19 ],
      [ "27131", 181 ],
      [ "27163", 1088 ],
      [ "20055", 103 ],
      [ "28137", 74 ],
      [ "42035", 41 ],
      [ "30089", 23 ],
      [ "40135", 152 ],
      [ "48223", 93 ],
      [ "31181", 7 ],
      [ "26073", 257 ],
      [ "26111", 172 ],
      [ "48277", 166 ],
      [ "28097", 19 ],
      [ "40137", 111 ],
      [ "39109", 271 ],
      [ "45033", 72 ],
      [ "26003", 20 ],
      [ "17145", 40 ],
      [ "39047", 63 ],
      [ "18011", 288 ],
      [ "18069", 109 ],
      [ "51065", 66 ],
      [ "48091", 682 ],
      [ "20009", 73 ],
      [ "48259", 167 ],
      [ "42119", 59 ],
      [ "17075", 84 ],
      [ "17081", 200 ],
      [ "12011", 3308 ],
      [ "18145", 141 ],
      [ "31047", 75 ],
      [ "12103", 1227 ],
      [ "45031", 132 ],
      [ "18005", 261 ],
      [ "45051", 741 ],
      [ "18073", 145 ],
      [ "18087", 56 ],
      [ "18133", 93 ],
      [ "31159", 537 ],
      [ "21037", 289 ],
      [ "27043", 43 ],
      [ "42073", 155 ],
      [ "35041", 86 ],
      [ "42055", 240 ],
      [ "31119", 183 ],
      [ "30077", 26 ],
      [ "47131", 117 ],
      [ "40027", 887 ],
      [ "39067", 23 ],
      [ "39065", 76 ],
      [ "39155", 429 ],
      [ "49021", 177 ],
      [ "17179", 616 ],
      [ "42063", 453 ],
      [ "48055", 269 ],
      [ "48053", 160 ],
      [ "48479", 300 ],
      [ "26159", 525 ],
      [ "38105", 126 ],
      [ "38017", 592 ],
      [ "26081", 9397 ],
      [ "35053", 60 ],
      [ "50005", 38 ],
      [ "45027", 87 ],
      [ "26119", 30 ],
      [ "22041", 57 ],
      [ "56025", 257 ],
      [ "20085", 46 ],
      [ "51177", 379 ],
      [ "31151", 32 ],
      [ "51063", 6 ],
      [ "51670", 129 ],
      [ "28155", 28 ],
      [ "18179", 77 ],
      [ "19085", 32 ],
      [ "37063", 199 ],
      [ "47117", 88 ],
      [ "17131", 25 ],
      [ "28079", 31 ],
      [ "28095", 72 ],
      [ "42069", 340 ],
      [ "55039", 144 ],
      [ "23023", 94 ],
      [ "42065", 52 ],
      [ "55003", 25 ],
      [ "16085", 107 ],
      [ "16049", 72 ],
      [ "48015", 183 ],
      [ "17053", 38 ],
      [ "26043", 38 ],
      [ "27019", 328 ],
      [ "21061", 33 ],
      [ "55053", 33 ],
      [ "39043", 234 ],
      [ "32023", 124 ],
      [ "17195", 120 ],
      [ "06027", 103 ],
      [ "06003", 1015 ],
      [ "06115", 327 ],
      [ "13151", 82 ],
      [ "21029", 170 ],
      [ "51061", 271 ],
      [ "47105", 125 ],
      [ "35006", 74 ],
      [ "48361", 199 ],
      [ "48119", 18 ],
      [ "49023", 28 ],
      [ "16041", 42 ],
      [ "19087", 75 ],
      [ "48419", 46 ],
      [ "36103", 193 ],
      [ "28041", 7 ],
      [ "17117", 168 ],
      [ "19083", 28 ],
      [ "19157", 52 ],
      [ "28085", 57 ],
      [ "18043", 277 ],
      [ "37181", 33 ],
      [ "48309", 1672 ],
      [ "48001", 197 ],
      [ "54045", 103 ],
      [ "35029", 80 ],
      [ "55015", 43 ],
      [ "19139", 255 ],
      [ "20191", 129 ],
      [ "16023", 10 ],
      [ "41067", 480 ],
      [ "21003", 76 ],
      [ "30099", 24 ],
      [ "08005", 169 ],
      [ "20017", 5 ],
      [ "26041", 49 ],
      [ "21141", 75 ],
      [ "47129", 27 ],
      [ "20051", 149 ],
      [ "17033", 37 ],
      [ "55089", 284 ],
      [ "26145", 491 ],
      [ "48025", 92 ],
      [ "18083", 63 ],
      [ "51073", 93 ],
      [ "21025", 13 ],
      [ "02185", 47 ],
      [ "17077", 548 ],
      [ "39127", 109 ],
      [ "29095", 134 ],
      [ "18161", 9 ],
      [ "18041", 36 ],
      [ "31097", 11 ],
      [ "28029", 59 ],
      [ "48451", 480 ],
      [ "47083", 18 ],
      [ "18105", 1015 ],
      [ "18109", 466 ],
      [ "26157", 139 ],
      [ "22065", 23 ],
      [ "42129", 869 ],
      [ "48011", 16 ],
      [ "51191", 166 ],
      [ "18017", 103 ],
      [ "26133", 67 ],
      [ "16047", 154 ],
      [ "16059", 41 ],
      [ "22075", 89 ],
      [ "22061", 217 ],
      [ "48337", 86 ],
      [ "48299", 81 ],
      [ "36081", 39 ],
      [ "48323", 96 ],
      [ "54033", 94 ],
      [ "54105", 17 ],
      [ "29189", 188 ],
      [ "29510", 70 ],
      [ "21211", 90 ],
      [ "26155", 204 ],
      [ "55043", 162 ],
      [ "51610", 94 ],
      [ "22101", 139 ],
      [ "18077", 73 ],
      [ "28141", 27 ],
      [ "51023", 87 ],
      [ "12001", 459 ],
      [ "41017", 100 ],
      [ "17177", 105 ],
      [ "47141", 350 ],
      [ "26109", 25 ],
      [ "19005", 18 ],
      [ "45071", 101 ],
      [ "51137", 85 ],
      [ "40125", 187 ],
      [ "37119", 1018 ],
      [ "51085", 341 ],
      [ "39169", 151 ],
      [ "19125", 72 ],
      [ "26033", 75 ],
      [ "18183", 114 ],
      [ "55117", 163 ],
      [ "22011", 149 ],
      [ "20111", 147 ],
      [ "51083", 95 ],
      [ "27103", 111 ],
      [ "51683", 197 ],
      [ "17027", 95 ],
      [ "21089", 44 ],
      [ "47145", 127 ],
      [ "47001", 193 ],
      [ "31155", 53 ],
      [ "54009", 109 ],
      [ "17055", 113 ],
      [ "22047", 52 ],
      [ "47003", 142 ],
      [ "54027", 31 ],
      [ "34039", 164 ],
      [ "24043", 38 ],
      [ "21113", 254 ],
      [ "19053", 40 ],
      [ "21117", 602 ],
      [ "21019", 109 ],
      [ "39063", 364 ],
      [ "39175", 44 ],
      [ "48475", 32 ],
      [ "23017", 80 ],
      [ "21205", 42 ],
      [ "39105", 54 ],
      [ "48005", 247 ],
      [ "31147", 15 ],
      [ "39073", 75 ],
      [ "26009", 53 ],
      [ "26135", 11 ],
      [ "26037", 160 ],
      [ "53035", 371 ],
      [ "20041", 66 ],
      [ "19031", 130 ],
      [ "39001", 51 ],
      [ "27119", 37 ],
      [ "22095", 158 ],
      [ "53063", 227 ],
      [ "21217", 35 ],
      [ "20087", 70 ],
      [ "48499", 144 ],
      [ "26069", 98 ],
      [ "18129", 62 ],
      [ "18165", 40 ],
      [ "28151", 173 ],
      [ "34003", 321 ],
      [ "22117", 77 ],
      [ "51071", 113 ],
      [ "54057", 46 ],
      [ "39005", 91 ],
      [ "39027", 114 ],
      [ "39159", 178 ],
      [ "39157", 94 ],
      [ "26005", 496 ],
      [ "55005", 83 ],
      [ "30057", 15 ],
      [ "19183", 242 ],
      [ "18071", 178 ],
      [ "25011", 162 ],
      [ "39003", 224 ],
      [ "55135", 61 ],
      [ "48325", 143 ],
      [ "47033", 51 ],
      [ "17181", 52 ],
      [ "47121", 29 ],
      [ "34021", 104 ],
      [ "01081", 11 ],
      [ "28105", 140 ],
      [ "40141", 30 ],
      [ "28083", 88 ],
      [ "54087", 55 ],
      [ "54055", 111 ],
      [ "19081", 17 ],
      [ "48185", 201 ],
      [ "54049", 105 ],
      [ "02130", 86 ],
      [ "12075", 59 ],
      [ "08049", 13 ],
      [ "22067", 57 ],
      [ "48197", 23 ],
      [ "48487", 80 ],
      [ "09005", 38 ],
      [ "04009", 89 ],
      [ "31079", 138 ],
      [ "20103", 501 ],
      [ "21199", 80 ],
      [ "47041", 79 ],
      [ "21073", 251 ],
      [ "19105", 52 ],
      [ "17165", 44 ],
      [ "18099", 108 ],
      [ "53047", 22 ],
      [ "39119", 216 ],
      [ "53011", 150 ],
      [ "26027", 178 ],
      [ "19179", 63 ],
      [ "12069", 289 ],
      [ "21057", 14 ],
      [ "42115", 67 ],
      [ "20147", 44 ],
      [ "13051", 142 ],
      [ "53067", 108 ],
      [ "21005", 85 ],
      [ "27005", 40 ],
      [ "44001", 134 ],
      [ "53075", 72 ],
      [ "13059", 44 ],
      [ "28107", 96 ],
      [ "26079", 51 ],
      [ "17189", 35 ],
      [ "53053", 545 ],
      [ "21099", 20 ],
      [ "48365", 69 ],
      [ "18125", 32 ],
      [ "37011", 10 ],
      [ "51175", 74 ],
      [ "40139", 83 ],
      [ "13127", 26 ],
      [ "55027", 142 ],
      [ "17003", 13 ],
      [ "47045", 201 ],
      [ "06101", 281 ],
      [ "38103", 5 ],
      [ "19167", 31 ],
      [ "37081", 213 ],
      [ "41061", 58 ],
      [ "51053", 82 ],
      [ "31179", 23 ],
      [ "47009", 276 ],
      [ "27013", 286 ],
      [ "31127", 52 ],
      [ "55049", 33 ],
      [ "48147", 108 ],
      [ "37099", 15 ],
      [ "27161", 27 ],
      [ "27147", 75 ],
      [ "27039", 59 ],
      [ "12081", 1903 ],
      [ "39071", 101 ],
      [ "32001", 80 ],
      [ "41003", 102 ],
      [ "20149", 65 ],
      [ "27141", 345 ],
      [ "48493", 147 ],
      [ "42105", 88 ],
      [ "19115", 51 ],
      [ "28073", 198 ],
      [ "30009", 18 ],
      [ "48163", 45 ],
      [ "20097", 16 ],
      [ "48031", 24 ],
      [ "02070", 65 ],
      [ "48043", 37 ],
      [ "13135", 541 ],
      [ "51790", 75 ],
      [ "18061", 98 ],
      [ "53029", 73 ],
      [ "18153", 36 ],
      [ "18007", 28 ],
      [ "28131", 32 ],
      [ "48401", 135 ],
      [ "28031", 45 ],
      [ "51125", 22 ],
      [ "48415", 53 ],
      [ "51099", 98 ],
      [ "26029", 53 ],
      [ "37101", 67 ],
      [ "37097", 76 ],
      [ "18051", 58 ],
      [ "37025", 151 ],
      [ "48149", 68 ],
      [ "21125", 85 ],
      [ "36007", 35 ],
      [ "37055", 52 ],
      [ "20101", 6 ],
      [ "20155", 396 ],
      [ "02164", 10 ],
      [ "02068", 28 ],
      [ "48227", 163 ],
      [ "31027", 26 ],
      [ "56007", 55 ],
      [ "55085", 65 ],
      [ "26057", 85 ],
      [ "47015", 30 ],
      [ "53045", 35 ],
      [ "39143", 152 ],
      [ "19107", 40 ],
      [ "27047", 66 ],
      [ "48071", 113 ],
      [ "19191", 27 ],
      [ "29203", 4 ],
      [ "37147", 56 ],
      [ "37133", 162 ],
      [ "55069", 51 ],
      [ "31167", 8 ],
      [ "48349", 208 ],
      [ "35021", 3 ],
      [ "42111", 83 ],
      [ "31121", 13 ],
      [ "30047", 72 ],
      [ "21017", 41 ],
      [ "09007", 45 ],
      [ "51159", 152 ],
      [ "20175", 87 ],
      [ "18031", 48 ],
      [ "48455", 37 ],
      [ "55023", 36 ],
      [ "48143", 192 ],
      [ "48093", 27 ],
      [ "28115", 21 ],
      [ "31125", 9 ],
      [ "37141", 28 ],
      [ "47073", 114 ],
      [ "51620", 45 ],
      [ "31093", 15 ],
      [ "21179", 67 ],
      [ "21185", 150 ],
      [ "48159", 23 ],
      [ "31033", 29 ],
      [ "40123", 64 ],
      [ "37195", 32 ],
      [ "45039", 43 ],
      [ "35025", 203 ],
      [ "53003", 6 ],
      [ "27033", 25 ],
      [ "47177", 341 ],
      [ "20015", 355 ],
      [ "40047", 141 ],
      [ "35003", 24 ],
      [ "47099", 79 ],
      [ "19025", 16 ],
      [ "30085", 30 ],
      [ "20165", 39 ],
      [ "28065", 21 ],
      [ "18121", 16 ],
      [ "17107", 133 ],
      [ "28145", 40 ],
      [ "18033", 163 ],
      [ "55093", 135 ],
      [ "49025", 28 ],
      [ "17175", 6 ],
      [ "19119", 28 ],
      [ "28001", 337 ],
      [ "30001", 42 ],
      [ "48343", 35 ],
      [ "35051", 48 ],
      [ "53041", 23 ],
      [ "37155", 26 ],
      [ "19071", 22 ],
      [ "51119", 28 ],
      [ "51163", 66 ],
      [ "20059", 115 ],
      [ "29043", 17 ],
      [ "48049", 162 ],
      [ "54065", 49 ],
      [ "51079", 43 ],
      [ "37035", 48 ],
      [ "20199", 2 ],
      [ "25007", 36 ],
      [ "13247", 44 ],
      [ "19161", 25 ],
      [ "05065", 1 ],
      [ "54109", 43 ],
      [ "48433", 3 ],
      [ "56037", 167 ],
      [ "20007", 12 ],
      [ "20207", 9 ],
      [ "20079", 194 ],
      [ "22119", 99 ],
      [ "42061", 54 ],
      [ "51097", 18 ],
      [ "08107", 11 ],
      [ "34001", 75 ],
      [ "48171", 90 ],
      [ "39131", 57 ],
      [ "54069", 485 ],
      [ "24041", 7 ],
      [ "19043", 32 ],
      [ "48287", 55 ],
      [ "39029", 129 ],
      [ "55001", 33 ],
      [ "48161", 64 ],
      [ "51147", 54 ],
      [ "48179", 95 ],
      [ "21049", 90 ],
      [ "41027", 512 ],
      [ "40051", 127 ],
      [ "48137", 7 ],
      [ "35011", 11 ],
      [ "31045", 21 ],
      [ "34025", 230 ],
      [ "18025", 11 ],
      [ "36047", 34 ],
      [ "30003", 14 ],
      [ "21223", 19 ],
      [ "55061", 24 ],
      [ "55029", 33 ],
      [ "48305", 46 ],
      [ "24033", 231 ],
      [ "27023", 35 ],
      [ "55129", 50 ],
      [ "20115", 45 ],
      [ "48335", 21 ],
      [ "53007", 44 ],
      [ "48241", 91 ],
      [ "37129", 105 ],
      [ "53001", 34 ],
      [ "48247", 13 ],
      [ "17153", 18 ],
      [ "28025", 81 ],
      [ "41053", 22 ],
      [ "05071", 3 ],
      [ "26015", 235 ],
      [ "37061", 23 ],
      [ "34031", 135 ],
      [ "12059", 18 ],
      [ "49047", 110 ],
      [ "48469", 277 ],
      [ "51025", 83 ],
      [ "31011", 8 ],
      [ "35027", 74 ],
      [ "55123", 31 ],
      [ "19189", 11 ],
      [ "41007", 51 ],
      [ "37031", 59 ],
      [ "24003", 143 ],
      [ "35007", 174 ],
      [ "28007", 34 ],
      [ "24025", 40 ],
      [ "12101", 405 ],
      [ "37197", 15 ],
      [ "37089", 36 ],
      [ "40153", 86 ],
      [ "19137", 21 ],
      [ "19185", 27 ],
      [ "45017", 35 ],
      [ "56031", 36 ],
      [ "51169", 56 ],
      [ "41035", 37 ],
      [ "51113", 17 ],
      [ "41065", 35 ],
      [ "47069", 55 ],
      [ "28139", 18 ],
      [ "48313", 91 ],
      [ "47077", 43 ],
      [ "19007", 35 ],
      [ "48127", 36 ],
      [ "48271", 8 ],
      [ "51173", 185 ],
      [ "53051", 7 ],
      [ "27121", 30 ],
      [ "38097", 23 ],
      [ "48239", 20 ],
      [ "48495", 29 ],
      [ "48253", 53 ],
      [ "18001", 59 ],
      [ "37069", 24 ],
      [ "48279", 60 ],
      [ "37071", 112 ],
      [ "47153", 27 ],
      [ "37017", 23 ],
      [ "37067", 161 ],
      [ "30039", 16 ],
      [ "48297", 21 ],
      [ "45053", 92 ],
      [ "34029", 103 ],
      [ "31065", 7 ],
      [ "31089", 21 ],
      [ "28117", 36 ],
      [ "05007", 67 ],
      [ "17095", 158 ],
      [ "02232", 10 ],
      [ "48133", 79 ],
      [ "51005", 27 ],
      [ "47063", 67 ],
      [ "29033", 2 ],
      [ "21221", 58 ],
      [ "48207", 21 ],
      [ "26095", 8 ],
      [ "42109", 41 ],
      [ "40043", 19 ],
      [ "20073", 25 ],
      [ "54103", 28 ],
      [ "27085", 82 ],
      [ "17137", 75 ],
      [ "27111", 81 ],
      [ "29037", 32 ],
      [ "35055", 93 ],
      [ "21193", 36 ],
      [ "27173", 16 ],
      [ "18047", 47 ],
      [ "13075", 11 ],
      [ "13223", 57 ],
      [ "48035", 95 ],
      [ "05037", 3 ],
      [ "18137", 50 ],
      [ "28015", 20 ],
      [ "47111", 28 ],
      [ "37135", 93 ],
      [ "21225", 57 ],
      [ "55113", 37 ],
      [ "37125", 22 ],
      [ "19129", 40 ],
      [ "22027", 26 ],
      [ "21001", 19 ],
      [ "48289", 74 ],
      [ "26113", 25 ],
      [ "28123", 45 ],
      [ "08073", 9 ],
      [ "55013", 24 ],
      [ "01077", 8 ],
      [ "36087", 51 ],
      [ "40091", 56 ],
      [ "26013", 10 ],
      [ "51045", 6 ],
      [ "05119", 64 ],
      [ "17045", 35 ],
      [ "47185", 91 ],
      [ "54013", 7 ],
      [ "12035", 93 ],
      [ "26105", 66 ],
      [ "54085", 16 ],
      [ "30097", 11 ],
      [ "20077", 11 ],
      [ "19177", 12 ],
      [ "", 8263859 ],
      [ null, 0 ],
      [ "16055", 1050 ],
      [ "49049", 2275 ],
      [ "33009", 287 ],
      [ "50027", 183 ],
      [ "26065", 1563 ],
      [ "39133", 481 ],
      [ "25005", 1465 ],
      [ "28089", 385 ],
      [ "42003", 5468 ],
      [ "51740", 748 ],
      [ "39049", 7977 ],
      [ "22051", 1601 ],
      [ "06073", 17853 ],
      [ "35061", 249 ],
      [ "42071", 804 ],
      [ "06065", 16198 ],
      [ "06067", 7872 ],
      [ "27003", 1495 ],
      [ "06029", 2333 ],
      [ "48085", 4799 ],
      [ "17043", 7811 ],
      [ "48029", 8379 ],
      [ "45069", 61 ],
      [ "48097", 161 ],
      [ "06001", 15728 ],
      [ "42029", 1252 ],
      [ "40101", 159 ],
      [ "40143", 1961 ],
      [ "48329", 619 ],
      [ "28021", 22 ],
      [ "28149", 155 ],
      [ "26099", 4363 ],
      [ "15009", 416 ],
      [ "28087", 133 ],
      [ "09011", 86 ],
      [ "06107", 885 ],
      [ "06079", 2043 ],
      [ "48201", 15497 ],
      [ "34035", 169 ],
      [ "47035", 88 ],
      [ "22055", 668 ],
      [ "06077", 3180 ],
      [ "20209", 1149 ],
      [ "17163", 1894 ],
      [ "42041", 781 ],
      [ "06041", 1549 ]
    ],
    "rowsReturned": 1000
  }
}